secretsanta/__init__.py
secretsanta/cli/__init__.py
secretsanta/cli/cli.py
secretsanta/main/__init__.py
secretsanta/main/core.py
secretsanta/main/funs.py
secretsanta/main/utils.py
secretsanta-0.2.0.dist-info/licenses/LICENSE
secretsanta-0.2.0.dist-info/METADATA
secretsanta-0.2.0.dist-info/WHEEL
secretsanta-0.2.0.dist-info/entry_points.txt
secretsanta-0.2.0.dist-info/top_level.txt
secretsanta-0.2.0.dist-info/RECORD
