Metadata-Version: 2.4
Name: secretsanta
Version: 0.2.0
Summary: Secret Santa randomizer
Author-email: Mirai Solutions <opensource@mirai-solutions.com>
License-Expression: MIT
Project-URL: Homepage, https://github.com/miraisolutions/secretsanta
Keywords: secret,santa
Classifier: Development Status :: 4 - Beta
Classifier: Operating System :: POSIX :: Linux
Classifier: Programming Language :: Python :: 3 :: Only
Classifier: Topic :: Games/Entertainment
Requires-Python: >=3.9
License-File: LICENSE
Requires-Dist: click
Requires-Dist: numpy
Dynamic: license-file
